{
  "1196541189223092246": {
    "heart": "游눞",
    "claimed": true,
    "channelId": "1182210332802961408"
  },
  "1196549204349292704": {
    "heart": "游눞",
    "claimed": true,
    "channelId": "1174219506663575604"
  },
  "1196570194399723561": {
    "heart": "仇벒잺",
    "claimed": true,
    "channelId": "1182210332802961408"
  },
  "1196570194458447972": {
    "heart": "游비",
    "claimed": true,
    "channelId": "1182210332802961408"
  },
  "1196643006305030315": {
    "heart": "游눞",
    "claimed": true,
    "channelId": "1182210332802961408"
  },
  "1196643006346952735": {
    "heart": "游눞",
    "claimed": true,
    "channelId": "1182210332802961408"
  },
  "1196643007592677397": {
    "heart": "游눝",
    "claimed": true,
    "channelId": "1182210332802961408"
  },
  "1196707674390274058": {
    "heart": "游눛",
    "claimed": true,
    "channelId": "1174219506663575604"
  },
  "1196707674868432996": {
    "heart": "游눞",
    "claimed": true,
    "channelId": "1174219506663575604"
  },
  "1196797469447688312": {
    "heart": "游눝",
    "claimed": true,
    "channelId": "1174219506663575604"
  },
  "1196797469518991441": {
    "heart": "游눞",
    "claimed": true,
    "channelId": "1174219506663575604"
  },
  "1196797469363818516": {
    "heart": "游눛",
    "claimed": true,
    "channelId": "1174219506663575604"
  },
  "1196831453607120957": {
    "heart": "仇벒잺",
    "claimed": true,
    "channelId": "1174219506663575604"
  },
  "1196883395096088617": {
    "heart": "仇벒잺",
    "claimed": true,
    "channelId": "1174219506663575604"
  },
  "1196891530007421038": {
    "heart": "仇벒잺",
    "claimed": true,
    "channelId": "1182880720008515667"
  },
  "1196891813252956173": {
    "heart": "游눜",
    "claimed": true,
    "channelId": "1182880720008515667"
  },
  "1196978138379456644": {
    "heart": "游비",
    "claimed": true,
    "channelId": "1182210332802961408"
  },
  "1196982903972823100": {
    "heart": "游눝",
    "claimed": true,
    "channelId": "1182210332802961408"
  },
  "1196986825101803580": {
    "heart": "游눜",
    "claimed": true,
    "channelId": "1174219506663575604"
  },
  "1196987763573137428": {
    "heart": "游비",
    "claimed": true,
    "channelId": "1182210332802961408"
  },
  "1197000630317875304": {
    "heart": "游눛",
    "claimed": true,
    "channelId": "1182210332802961408"
  },
  "1197002850232979607": {
    "heart": "游비",
    "claimed": true,
    "channelId": "1182210332802961408"
  },
  "1197014550147502212": {
    "heart": "游눞",
    "claimed": true,
    "channelId": "1182210332802961408"
  },
  "1197016250992295988": {
    "heart": "仇벒잺",
    "claimed": true,
    "channelId": "1182880720008515667"
  },
  "1197017343847567431": {
    "heart": "游비",
    "claimed": true,
    "channelId": "1182880720008515667"
  },
  "1197181915447447685": {
    "heart": "仇벒잺",
    "claimed": true,
    "channelId": "1174219506663575604"
  },
  "1197181915489382410": {
    "heart": "游눜",
    "claimed": true,
    "channelId": "1174219506663575604"
  },
  "1197185941819899914": {
    "heart": "游눜",
    "claimed": true,
    "channelId": "1174219506663575604"
  },
  "1197185941882802247": {
    "heart": "游비",
    "claimed": true,
    "channelId": "1174219506663575604"
  },
  "1197186672538951711": {
    "heart": "游비",
    "claimed": true,
    "channelId": "1174219506663575604"
  },
  "1197186672547348490": {
    "heart": "游눛",
    "claimed": true,
    "channelId": "1174219506663575604"
  },
  "1197190104578527302": {
    "heart": "游비",
    "claimed": true,
    "channelId": "1174219506663575604"
  },
  "1197190104893100072": {
    "heart": "游눛",
    "claimed": true,
    "channelId": "1174219506663575604"
  },
  "1197191038733930506": {
    "heart": "游눛",
    "claimed": true,
    "channelId": "1174219506663575604"
  },
  "1197191039061069864": {
    "heart": "游눛",
    "claimed": true,
    "channelId": "1174219506663575604"
  },
  "1197205540955238563": {
    "heart": "游눜",
    "claimed": true,
    "channelId": "1174219506663575604"
  },
  "1197205541882171433": {
    "heart": "游눜",
    "claimed": true,
    "channelId": "1174219506663575604"
  },
  "1197218078447128643": {
    "heart": "游눛",
    "claimed": true,
    "channelId": "1174219506663575604"
  },
  "1197218081248911360": {
    "heart": "游눛",
    "claimed": true,
    "channelId": "1174219506663575604"
  },
  "1197225031399387266": {
    "heart": "游눛",
    "claimed": true,
    "channelId": "1182210332802961408"
  },
  "1197225031739113482": {
    "heart": "游눜",
    "claimed": true,
    "channelId": "1182210332802961408"
  },
  "1197228540442181732": {
    "heart": "游비",
    "claimed": true,
    "channelId": "1174219506663575604"
  },
  "1197228540924542987": {
    "heart": "游눜",
    "claimed": true,
    "channelId": "1174219506663575604"
  },
  "1197228925571571793": {
    "heart": "游눞",
    "claimed": true,
    "channelId": "1182210332802961408"
  },
  "1197228925680632070": {
    "heart": "游눛",
    "claimed": true,
    "channelId": "1182210332802961408"
  },
  "1197334618945372180": {
    "heart": "游비",
    "claimed": true,
    "channelId": "1182210332802961408"
  },
  "1197334619444490371": {
    "heart": "游눞",
    "claimed": true,
    "channelId": "1182210332802961408"
  },
  "1197334619977162752": {
    "heart": "游눛",
    "claimed": true,
    "channelId": "1182210332802961408"
  },
  "1197335201664208906": {
    "heart": "仇벒잺",
    "claimed": true,
    "channelId": "1182210332802961408"
  },
  "1197335201668403210": {
    "heart": "仇벒잺",
    "claimed": true,
    "channelId": "1182210332802961408"
  },
  "1197335201966198966": {
    "heart": "游눞",
    "claimed": true,
    "channelId": "1182210332802961408"
  },
  "1197336692760248483": {
    "heart": "游눞",
    "claimed": true,
    "channelId": "1182210332802961408"
  },
  "1197336693137748068": {
    "heart": "游눞",
    "claimed": true,
    "channelId": "1182210332802961408"
  },
  "1197336693221625936": {
    "heart": "游눝",
    "claimed": true,
    "channelId": "1182210332802961408"
  },
  "1197338143179948053": {
    "heart": "游눛",
    "claimed": true,
    "channelId": "1182210332802961408"
  },
  "1197339642127724657": {
    "heart": "游눜",
    "claimed": true,
    "channelId": "1182210332802961408"
  },
  "1197340216072081548": {
    "heart": "游비",
    "claimed": true,
    "channelId": "1182210332802961408"
  },
  "1197341632706650212": {
    "heart": "仇벒잺",
    "claimed": true,
    "channelId": "1182210332802961408"
  },
  "1197362003119964170": {
    "heart": "游눞",
    "claimed": true,
    "channelId": "1174219506663575604"
  },
  "1197363453476753408": {
    "heart": "游눜",
    "claimed": true,
    "channelId": "1174219506663575604"
  },
  "1197363813259952178": {
    "heart": "游눝",
    "claimed": true,
    "channelId": "1174219506663575604"
  },
  "1197410150177308825": {
    "heart": "游눜",
    "claimed": true,
    "channelId": "1182210332802961408"
  }
}